RocketSim.abi3.so
rocketsim-2.1.1.post4.dist-info/METADATA
rocketsim-2.1.1.post4.dist-info/WHEEL
rocketsim-2.1.1.post4.dist-info/top_level.txt
rocketsim-2.1.1.post4.dist-info/RECORD
rocketsim-2.1.1.post4.dist-info/license/LICENSE
