Metadata-Version: 2.1
Name: rocketsim
Version: 2.1.1.post4
Summary: This is Rocket League!
Requires-Python: >= 3.9
License-File: LICENSE
Requires-Dist: cmeel
Requires-Dist: numpy
Provides-Extra: build
Requires-Dist: numpy>=2.0,<3 ; extra == "build"
